./.dockerignore
./.env.example
./.gitignore
./.python-version
./CLAUDE.md
./Dockerfile
./PKG-INFO
./README.md
./config.py
./deploy.sh
./docker-compose.yml
./docker-status-mqtt-homeassistant.xml
./docker_manager.py
./healthcheck.py
./home-assistant-screenshot.png
./icon.png
./main.py
./pyproject.toml
./test_docker_manager.py
./uv.lock
./.github/workflows/docker.yml
./.github/workflows/publish.yml
./.vscode/launch.json
docker_status_mqtt_homeassistant-0.4.1.dist-info/METADATA
docker_status_mqtt_homeassistant-0.4.1.dist-info/WHEEL
docker_status_mqtt_homeassistant-0.4.1.dist-info/entry_points.txt
docker_status_mqtt_homeassistant-0.4.1.dist-info/RECORD
