Metadata-Version: 2.4
Name: docker-status-mqtt-homeassistant
Version: 0.4.1
Summary: Publish the status of Docker containers to an MQTT broker for Home Assistant integration
Project-URL: Homepage, https://github.com/pcarorevuelta/docker-status-mqtt-homeassistant
Project-URL: Repository, https://github.com/pcarorevuelta/docker-status-mqtt-homeassistant
Project-URL: Issues, https://github.com/pcarorevuelta/docker-status-mqtt-homeassistant/issues
Author-email: Pablo Caro Revuelta <pcarorevuelta@gmail.com>
License: MIT
Keywords: containers,docker,homeassistant,monitoring,mqtt
Classifier: Development Status :: 4 - Beta
Classifier: Intended Audience :: System Administrators
Classifier: License :: OSI Approved :: MIT License
Classifier: Operating System :: OS Independent
Classifier: Programming Language :: Python :: 3
Classifier: Programming Language :: Python :: 3.12
Classifier: Topic :: Home Automation
Classifier: Topic :: System :: Monitoring
Requires-Python: >=3.12
Requires-Dist: docker>=7.1.0
Requires-Dist: paho-mqtt>=2.1.0
Requires-Dist: paramiko>=3.5.0
